Metadata-Version: 2.1
Name: git-runstats
Version: 0.16.0
Summary: Runs through git history and shows most active users.
Home-page: https://github.com/adfinis-sygroup/git-runstats
Author: Jean-Louis Fuchs
Author-email: jean-louis.fuchs@adfinis-sygroup.ch
License: AGPL-3.0-or-later
Platform: UNKNOWN
Classifier: License :: OSI Approved :: GNU Affero General Public License v3 or later (AGPLv3+)
Classifier: Programming Language :: Python
Classifier: Programming Language :: Python :: 3
Classifier: Programming Language :: Python :: 3.8
Classifier: Programming Language :: Python :: Implementation :: CPython
Classifier: Programming Language :: Python :: Implementation :: PyPy
Requires-Python: >=3.8.0
